{
  "project": "TRADESIGHT",
  "mode": "BuildOS",
  "current_plan": "capability-build-v2",
  "current_step": 15,
  "next_task": "15-report-studio",
  "status": "ready",
  "last_completed": "14-assessment-intelligence",
  "last_commit_summary": "Added Assessment Intelligence with risk scoring, evidence completeness scoring, priority calculation, evidence-aware assessment creation, and UI score display.",
  "blocker": null,
  "operating_sequence": [
    "Read BuildOS state",
    "Read roadmap and quality gates",
    "Inspect repository",
    "Build one operational increment",
    "Commit",
    "Update BuildOS",
    "Stop"
  ]
}
